bson-stubs/__init__.pyi
bson-stubs/binary.pyi
bson-stubs/code.pyi
bson-stubs/codec_options.pyi
bson-stubs/dbref.pyi
bson-stubs/decimal128.pyi
bson-stubs/errors.pyi
bson-stubs/int64.pyi
bson-stubs/json_util.pyi
bson-stubs/max_key.pyi
bson-stubs/min_key.pyi
bson-stubs/objectid.pyi
bson-stubs/raw_bson.pyi
bson-stubs/regex.pyi
bson-stubs/son.pyi
bson-stubs/timestamp.pyi
bson-stubs/tz_util.pyi
gridfs-stubs/__init__.pyi
gridfs-stubs/errors.pyi
gridfs-stubs/grid_file.pyi
pymongo-stubs/__init__.pyi
pymongo-stubs/bulk.pyi
pymongo-stubs/change_stream.pyi
pymongo-stubs/client_session.pyi
pymongo-stubs/collation.pyi
pymongo-stubs/collection.pyi
pymongo-stubs/command_cursor.pyi
pymongo-stubs/common.pyi
pymongo-stubs/cursor.pyi
pymongo-stubs/cursor_manager.pyi
pymongo-stubs/database.pyi
pymongo-stubs/driver_info.pyi
pymongo-stubs/encryption.pyi
pymongo-stubs/encryption_options.pyi
pymongo-stubs/errors.pyi
pymongo-stubs/event_loggers.pyi
pymongo-stubs/ismaster.pyi
pymongo-stubs/mongo_client.pyi
pymongo-stubs/mongo_replica_set_client.pyi
pymongo-stubs/monitoring.pyi
pymongo-stubs/operations.pyi
pymongo-stubs/read_concern.pyi
pymongo-stubs/read_preferences.pyi
pymongo-stubs/results.pyi
pymongo-stubs/server_description.pyi
pymongo-stubs/server_type.pyi
pymongo-stubs/son_manipulator.pyi
pymongo-stubs/topology_description.pyi
pymongo-stubs/uri_parser.pyi
pymongo-stubs/write_concern.pyi
pymongo_stubs-0.2.0.dist-info/LICENSE
pymongo_stubs-0.2.0.dist-info/METADATA
pymongo_stubs-0.2.0.dist-info/WHEEL
pymongo_stubs-0.2.0.dist-info/top_level.txt
pymongo_stubs-0.2.0.dist-info/RECORD
