Metadata-Version: 2.1
Name: pymongo-stubs
Version: 0.2.0
Summary: Experimental stub files for PyMongo
Home-page: https://github.com/mongodb-labs/pymongo-stubs
Author: Shane Harvey
Author-email: drivers-python-noreply@mongodb.com
License: Apache License, Version 2.0
Keywords: mongo,mongodb,pymongo,bson,gridfs
Platform: UNKNOWN
Classifier: Development Status :: 3 - Alpha
Classifier: Intended Audience :: Developers
Classifier: License :: OSI Approved :: Apache Software License
Classifier: Operating System :: MacOS :: MacOS X
Classifier: Operating System :: Microsoft :: Windows
Classifier: Operating System :: POSIX
Classifier: Programming Language :: Python :: 3
Classifier: Programming Language :: Python :: 3.6
Classifier: Programming Language :: Python :: 3.7
Classifier: Programming Language :: Python :: 3.8
Classifier: Programming Language :: Python :: 3.9
Classifier: Topic :: Database
Classifier: Typing :: Typed
Requires-Python: >=3.6
License-File: LICENSE
